keystone_rxt/rackspace.py
keystone_rxt-0.0.5.dist-info/AUTHORS
keystone_rxt-0.0.5.dist-info/METADATA
keystone_rxt-0.0.5.dist-info/WHEEL
keystone_rxt-0.0.5.dist-info/entry_points.txt
keystone_rxt-0.0.5.dist-info/pbr.json
keystone_rxt-0.0.5.dist-info/top_level.txt
keystone_rxt-0.0.5.dist-info/RECORD
