Metadata-Version: 2.2
Name: keystone_rxt
Version: 0.0.5
Summary: OpenStack Identity plugin for Rackspace Technologies
Home-page: https://github.com/rackerlabs/keystone-rxt
Author: Kevin Carter
Author-email: kevin.carter@rackspace.com
Classifier: Environment :: OpenStack
Classifier: Intended Audience :: Information Technology
Classifier: Intended Audience :: System Administrators
Classifier: License :: OSI Approved :: Apache Software License
Classifier: Operating System :: POSIX :: Linux
Classifier: Programming Language :: Python
Classifier: Programming Language :: Python :: Implementation :: CPython
Classifier: Programming Language :: Python :: 3 :: Only
Classifier: Programming Language :: Python :: 3
Classifier: Programming Language :: Python :: 3.11
Requires-Python: >=3.8
License-File: AUTHORS
Dynamic: author
Dynamic: author-email
Dynamic: classifier
Dynamic: description
Dynamic: home-page
Dynamic: requires-python
Dynamic: summary
